a2s/__init__.py
a2s-1.0.0.dist-info/LICENSE
a2s-1.0.0.dist-info/METADATA
a2s-1.0.0.dist-info/WHEEL
a2s-1.0.0.dist-info/top_level.txt
a2s-1.0.0.dist-info/RECORD
