Metadata-Version: 2.1
Name: a2s
Version: 1.0.0
Summary: Convert python async function to a sync function for calling from a normal function in an existing event loop
Home-page: https://github.com/plter/a2s
Author: plter
Author-email: xtiqin@163.com
License: UNKNOWN
Project-URL: Bug Tracker, https://github.com/plter/a2s/issues
Platform: UNKNOWN
Classifier: Programming Language :: Python :: 3
Classifier: License :: OSI Approved :: MIT License
Classifier: Operating System :: OS Independent
Requires-Python: >=3.8
License-File: LICENSE
